deletar/__init__.py
deletar/a.py
deletar/main.py
deletar/simple_calculator.py
deletar/simple_calculator_renatomarianoo.py
simple_calculator_renatomarianoo/__init__.py
simple_calculator_renatomarianoo/calculator.py
simple_calculator_renatomarianoo/simple_calculator_renatomarianoo.py
simple_calculator_renatomarianoo/tests/__init__.py
simple_calculator_renatomarianoo/tests/tests.py
simple_calculator_renatomarianoo-0.5.dist-info/METADATA
simple_calculator_renatomarianoo-0.5.dist-info/WHEEL
simple_calculator_renatomarianoo-0.5.dist-info/top_level.txt
simple_calculator_renatomarianoo-0.5.dist-info/RECORD
