Metadata-Version: 2.1
Name: simple-calculator-renatomarianoo
Version: 0.5
Summary: Simple Calculator to add, subtract, multiply, divide, exponentiate and take the n root
Author: Renato Mariano
Author-email: relucasmariano@gmail.com
